veils/__init__.py
veils/_async_dummy.py
veils/memo.py
veils/unpiercable.py
veils/veil.py
veils/veil_factory.py
veils-0.2.1.dist-info/LICENSE
veils-0.2.1.dist-info/WHEEL
veils-0.2.1.dist-info/METADATA
veils-0.2.1.dist-info/RECORD
