Metadata-Version: 2.1
Name: veils
Version: 0.2.1
Summary: Python Veil Objects
Home-page: https://github.com/monomonedula/veil
License: MIT
Keywords: decorator,dto,memoization,utility
Author: monomonedula
Author-email: valh@tuta.io
Requires-Python: >=3.6,<4.0
Classifier: License :: OSI Approved :: MIT License
Classifier: Programming Language :: Python :: 3
Classifier: Programming Language :: Python :: 3.6
Classifier: Programming Language :: Python :: 3.7
Classifier: Programming Language :: Python :: 3.8
Classifier: Programming Language :: Python :: 3.9
Requires-Dist: cachetools (>=4.2.0,<5.0.0)
Requires-Dist: wrapt (>=1.12.1,<2.0.0)
Project-URL: Repository, https://github.com/monomonedula/veil
